{
  "$schema": "https://json.schemastore.org/tsconfig",
  "compilerOptions": {
    "target": "ES2023",
    "useDefineForClassFields": true,
    "module": "ESNext",
    "moduleResolution": "Bundler",
    "allowImportingTsExtensions": true,
    "resolveJsonModule": true,
    "verbatimModuleSyntax": true,
    "isolatedModules": true,
    "moduleDetection": "force",
    "noEmit": true,
    "strict": true,
    "skipLibCheck": true,
    "noFallthroughCasesInSwitch": true,
    "noUncheckedIndexedAccess": true,
    "noUnusedLocals": true,
    "noUnusedParameters": true,
    "erasableSyntaxOnly": true
  }
}
